setup.py
Pycn/__init__.py
Pycn/基础操作.py
Pycn/文件操作.py
Pycn/用户界面.py
Pycn/输入输出.py
Pycn/错误类型.py
Pycn.egg-info/PKG-INFO
Pycn.egg-info/SOURCES.txt
Pycn.egg-info/dependency_links.txt
Pycn.egg-info/top_level.txt