Metadata-Version: 1.0
Name: Pycn
Version: 0.0.1
Summary: 王若宇出品的中文python库，用中文写Python~初来乍到，持续更新。
Home-page: https://github.com/
Author: Ruoyu Wang
Author-email: wangkang@139.com
License: MIT License
Platform: UNKNOWN
